{
  "type": "FeatureCollection",
  "features": [
    {
      "type": "Feature",
      "geometry": {
        "type": "Point",
        "coordinates": [
          99.04833,
          19.93139
        ]
      },
      "properties": {
        "date": "06/26/2026",
        "metric": "min_temp",
        "value": 20.3,
        "station": "ดอยอ่างขาง",
        "province": "เชียงใหม่"
      }
    },
    {
      "type": "Feature",
      "geometry": {
        "type": "Point",
        "coordinates": [
          104.061,
          17.12503
        ]
      },
      "properties": {
        "date": "06/26/2026",
        "metric": "max_temp",
        "value": 35.6,
        "station": "สกลนคร สกษ.",
        "province": "สกลนคร"
      }
    },
    {
      "type": "Feature",
      "geometry": {
        "type": "Point",
        "coordinates": [
          100.605,
          13.91917
        ]
      },
      "properties": {
        "date": "06/26/2026",
        "metric": "max_rainfall_24hr",
        "value": 40.4,
        "station": "สนามบินดอนเมือง",
        "province": "กรุงเทพมหานคร"
      }
    }
  ]
}