{
  "type": "FeatureCollection",
  "features": [
    {
      "type": "Feature",
      "geometry": {
        "type": "Point",
        "coordinates": [
          99.04833,
          19.93139
        ]
      },
      "properties": {
        "date": "06/24/2026",
        "metric": "min_temp",
        "value": 22.5,
        "station": "ดอยอ่างขาง",
        "province": "เชียงใหม่"
      }
    },
    {
      "type": "Feature",
      "geometry": {
        "type": "Point",
        "coordinates": [
          101.18736,
          15.26667
        ]
      },
      "properties": {
        "date": "06/24/2026",
        "metric": "max_temp",
        "value": 39.0,
        "station": "บัวชุม  ",
        "province": "ลพบุรี"
      }
    },
    {
      "type": "Feature",
      "geometry": {
        "type": "Point",
        "coordinates": [
          102.87808,
          11.78033
        ]
      },
      "properties": {
        "date": "06/24/2026",
        "metric": "max_rainfall",
        "value": 17.4,
        "station": "ตราด",
        "province": "ตราด"
      }
    }
  ]
}